rysftp/__init__.py
rysftp/ctx.py
rysftp/errors.py
rysftp/requests.py
rysftp/sftp.py
rysftp/utils.py
RySftp-0.0.10.dist-info/LICENSE
RySftp-0.0.10.dist-info/METADATA
RySftp-0.0.10.dist-info/WHEEL
RySftp-0.0.10.dist-info/top_level.txt
RySftp-0.0.10.dist-info/RECORD
