Metadata-Version: 2.1
Name: RySftp
Version: 0.0.10
Summary: simple, asynchronous sftp operations
Home-page: https://github.com/riptusk331/rysftp
Author: Ryan P Joyce
Author-email: ryan.joyce.88@gmail.com
License: UNKNOWN
Platform: UNKNOWN
Classifier: Programming Language :: Python :: 3
Classifier: License :: OSI Approved :: MIT License
Classifier: Operating System :: OS Independent
Requires-Python: >=3.8.5
Requires-Dist: paramiko (>=2.7.2)
Requires-Dist: Werkzeug (>=1.0.1)
